universi/__init__.py
universi/_utils.py
universi/codegen.py
universi/exceptions.py
universi/fields.py
universi/header.py
universi/py.typed
universi/routing.py
universi/structure/__init__.py
universi/structure/common.py
universi/structure/data.py
universi/structure/endpoints.py
universi/structure/enums.py
universi/structure/schemas.py
universi/structure/versions.py
universi-2.0.1.dist-info/LICENSE
universi-2.0.1.dist-info/WHEEL
universi-2.0.1.dist-info/METADATA
universi-2.0.1.dist-info/RECORD
